fakereal/__init__.py
fakereal/fakereal.py
fakereal/test_seedpy.py
fakereal-0.2.1.dist-info/METADATA
fakereal-0.2.1.dist-info/WHEEL
fakereal-0.2.1.dist-info/top_level.txt
fakereal-0.2.1.dist-info/RECORD
