Metadata-Version: 2.1
Name: fakereal
Version: 0.2.1
Summary: A Python library for seeding databases with random realistic test data.
Home-page: https://github.com/yousbot/fakereal
Author: Youssef Sbai Idrissi
Author-email: sbaiidrissiyoussef@gmail.com
Classifier: Development Status :: 3 - Alpha
Classifier: Intended Audience :: Developers
Classifier: License :: OSI Approved :: MIT License
Classifier: Programming Language :: Python :: 3
Classifier: Programming Language :: Python :: 3.6
Classifier: Programming Language :: Python :: 3.7
Classifier: Programming Language :: Python :: 3.8
Classifier: Programming Language :: Python :: 3.9
Requires-Python: >=3.6
Requires-Dist: peewee
Requires-Dist: Faker
